lazycache/.tmp_cache/foo_1 2_.pkl
lazycache/.tmp_cache/foo_3 4_.pkl
lazycache/.tmp_cache/foo__a 1 b 2.pkl
lazycache/__init__.py
lazycache/cache.py
lazycache-0.1.1.dist-info/METADATA
lazycache-0.1.1.dist-info/WHEEL
lazycache-0.1.1.dist-info/RECORD
